NOTICE
fastchecks/__init__.py
fastchecks/check.py
fastchecks/cli.py
fastchecks/conf.py
fastchecks/log.py
fastchecks/meta.py
fastchecks/runner.py
fastchecks/sockets/__init__.py
fastchecks/sockets/postgres/__init__.py
fastchecks/sockets/postgres/schema/down.sql
fastchecks/sockets/postgres/schema/up.sql
fastchecks/types.py
fastchecks/util.py
fastchecks/vutil.py
fastchecks-0.2.2.dist-info/LICENSE
fastchecks-0.2.2.dist-info/METADATA
fastchecks-0.2.2.dist-info/WHEEL
fastchecks-0.2.2.dist-info/entry_points.txt
fastchecks-0.2.2.dist-info/RECORD
