Metadata-Version: 2.1
Name: fastchecks
Version: 0.2.2
Summary: 🚥 Fast website monitoring backend service
Home-page: https://github.com/juanmirocks/fastchecks
License: Apache-2.0
Author: Dr. Juan Miguel Cejuela
Author-email: i@juanmi.rocks
Requires-Python: >=3.11,<4.0
Classifier: License :: OSI Approved :: Apache Software License
Classifier: Programming Language :: Python :: 3
Classifier: Programming Language :: Python :: 3.11
Requires-Dist: aiohttp (>=3.8.4,<4.0.0)
Requires-Dist: apscheduler (==4.0.0a2)
Requires-Dist: google-re2 (>=1.0,<2.0)
Requires-Dist: psycopg[binary,pool] (>=3.1.9,<4.0.0)
Requires-Dist: pydantic (>=2.0.1,<3.0.0)
Project-URL: Repository, https://github.com/juanmirocks/fastchecks
